README.rst
setup.py
sparkworks_client/__init__.py
sparkworks_client/api_client.py
sparkworks_client/configuration.py
sparkworks_client/rest.py
sparkworks_client/api/__init__.py
sparkworks_client/api/command_api.py
sparkworks_client/api/data_api.py
sparkworks_client/api/gateway_api.py
sparkworks_client/api/group_api.py
sparkworks_client/api/participatory_sensing_api.py
sparkworks_client/api/phenomenon_api.py
sparkworks_client/api/registry_api.py
sparkworks_client/api/resource_api.py
sparkworks_client/api/smart_work_api.py
sparkworks_client/api/unit_api.py
sparkworks_client/api/unit_conversion_api.py
sparkworks_client/models/__init__.py
sparkworks_client/models/a_participatory_sensing_resource_request_api_model.py
sparkworks_client/models/analytics_resource_data_response_dtoapi_model.py
sparkworks_client/models/collection_of_data_query_criteria_request_api_model.py
sparkworks_client/models/command_api_model.py
sparkworks_client/models/food_diary_data_criteria_dto.py
sparkworks_client/models/food_diary_dto.py
sparkworks_client/models/food_diary_dto_created_time_zone.py
sparkworks_client/models/gateway_create_dto.py
sparkworks_client/models/gateway_dto.py
sparkworks_client/models/gateway_query_dto.py
sparkworks_client/models/group_create_dto.py
sparkworks_client/models/group_dto.py
sparkworks_client/models/group_node_dto.py
sparkworks_client/models/group_update_dto.py
sparkworks_client/models/list_of_participatory_sensing_data_api_model.py
sparkworks_client/models/list_of_query_criteria_within_a_timeframe_request_api_model.py
sparkworks_client/models/participatory_sensing_data_api_model.py
sparkworks_client/models/phenomenon_create_dto.py
sparkworks_client/models/phenomenon_dto.py
sparkworks_client/models/phenomenon_query_dto.py
sparkworks_client/models/phenomenon_update_dto.py
sparkworks_client/models/publish_data_dtoapi_model.py
sparkworks_client/models/publish_data_list_dtoapi_model.py
sparkworks_client/models/query_latest_resource_data_dtoapi_model.py
sparkworksrest.egg-info/PKG-INFO
sparkworksrest.egg-info/SOURCES.txt
sparkworksrest.egg-info/dependency_links.txt
sparkworksrest.egg-info/requires.txt
sparkworksrest.egg-info/top_level.txt
