Metadata-Version: 1.0
Name: sparkworksrest
Version: 1.0.14
Summary: A client library for the sparkworks rest api
Home-page: https://sparkworksnet.github.io/sparkworksrest/
Author: UNKNOWN
Author-email: info@sparkworks.net
License: UNKNOWN
Keywords: Swagger,SparkWorks Core API
Platform: UNKNOWN
